/* Auto-generated by Tools/scripts/generate_opcode_h.py from Lib/opcode.py */
#ifndef Py_OPCODE_H
#define Py_OPCODE_H
#ifdef __cplusplus
extern "C" {
#endif


    /* Instruction opcodes for compiled code */
#define POP_TOP                   1
#define ROT_TWO                   2
#define ROT_THREE                 3
#define DUP_TOP                   4
#define DUP_TOP_TWO               5
#define ROT_FOUR                  6
#define NOP                       9
#define UNARY_POSITIVE           10
#define UNARY_NEGATIVE           11
#define UNARY_NOT                12
#define UNARY_INVERT             15
#define BINARY_MATRIX_MULTIPLY   16
#define INPLACE_MATRIX_MULTIPLY  17
#define BINARY_POWER             19
#define BINARY_MULTIPLY          20
#define BINARY_MODULO            22
#define BINARY_ADD               23
#define BINARY_SUBTRACT          24
#define BINARY_SUBSCR            25
#define BINARY_FLOOR_DIVIDE      26
#define BINARY_TRUE_DIVIDE       27
#define INPLACE_FLOOR_DIVIDE     28
#define INPLACE_TRUE_DIVIDE      29
#define GET_LEN                  30
#define MATCH_MAPPING            31
#define MATCH_SEQUENCE           32
#define MATCH_KEYS               33
#define COPY_DICT_WITHOUT_KEYS   34
#define WITH_EXCEPT_START        49
#define GET_AITER                50
#define GET_ANEXT                51
#define BEFORE_ASYNC_WITH        52
#define END_ASYNC_FOR            54
#define INPLACE_ADD              55
#define INPLACE_SUBTRACT         56
#define INPLACE_MULTIPLY         57
#define INPLACE_MODULO           59
#define STORE_SUBSCR             60
#define DELETE_SUBSCR            61
#define BINARY_LSHIFT            62
#define BINARY_RSHIFT            63
#define BINARY_AND               64
#define BINARY_XOR               65
#define BINARY_OR                66
#define INPLACE_POWER            67
#define GET_ITER                 68
#define GET_YIELD_FROM_ITER      69
#define PRINT_EXPR               70
#define LOAD_BUILD_CLASS         71
#define YIELD_FROM               72
#define GET_AWAITABLE            73
#define LOAD_ASSERTION_ERROR     74
#define INPLACE_LSHIFT           75
#define INPLACE_RSHIFT           76
#define INPLACE_AND              77
#define INPLACE_XOR              78
#define INPLACE_OR               79
#define LIST_TO_TUPLE            82
#define RETURN_VALUE             83
#define IMPORT_STAR              84
#define SETUP_ANNOTATIONS        85
#define YIELD_VALUE              86
#define POP_BLOCK                87
#define POP_EXCEPT               89
#define HAVE_ARGUMENT            90
#define STORE_NAME               90
#define DELETE_NAME              91
#define UNPACK_SEQUENCE          92
#define FOR_ITER                 93
#define UNPACK_EX                94
#define STORE_ATTR               95
#define DELETE_ATTR              96
#define STORE_GLOBAL             97
#define DELETE_GLOBAL            98
#define ROT_N                    99
#define LOAD_CONST              100
#define LOAD_NAME               101
#define BUILD_TUPLE             102
#define BUILD_LIST              103
#define BUILD_SET               104
#define BUILD_MAP               105
#define LOAD_ATTR               106
#define COMPARE_OP              107
#define IMPORT_NAME             108
#define IMPORT_FROM             109
#define JUMP_FORWARD            110
#define JUMP_IF_FALSE_OR_POP    111
#define JUMP_IF_TRUE_OR_POP     112
#define JUMP_ABSOLUTE           113
#define POP_JUMP_IF_FALSE       114
#define POP_JUMP_IF_TRUE        115
#define LOAD_GLOBAL             116
#define IS_OP                   117
#define CONTAINS_OP             118
#define RERAISE                 119
#define JUMP_IF_NOT_EXC_MATCH   121
#define SETUP_FINALLY           122
#define LOAD_FAST               124
#define STORE_FAST              125
#define DELETE_FAST             126
#define GEN_START               129
#define RAISE_VARARGS           130
#define CALL_FUNCTION           131
#define MAKE_FUNCTION           132
#define BUILD_SLICE             133
#define LOAD_CLOSURE            135
#define LOAD_DEREF              136
#define STORE_DEREF             137
#define DELETE_DEREF            138
#define CALL_FUNCTION_KW        141
#define CALL_FUNCTION_EX        142
#define SETUP_WITH              143
#define EXTENDED_ARG            144
#define LIST_APPEND             145
#define SET_ADD                 146
#define MAP_ADD                 147
#define LOAD_CLASSDEREF         148
#define MATCH_CLASS             152
#define SETUP_ASYNC_WITH        154
#define FORMAT_VALUE            155
#define BUILD_CONST_KEY_MAP     156
#define BUILD_STRING            157
#define INVOKE_METHOD           158
#define LOAD_FIELD              159
#define LOAD_METHOD             160
#define CALL_METHOD             161
#define LIST_EXTEND             162
#define SET_UPDATE              163
#define DICT_MERGE              164
#define DICT_UPDATE             165
#define STORE_FIELD             166
#define SEQUENCE_REPEAT         167
#define CAST                    170
#define LOAD_LOCAL              171
#define STORE_LOCAL             172
#define INT_LOAD_CONST_OLD      173
#define PRIMITIVE_BOX           174
#define POP_JUMP_IF_ZERO        175
#define POP_JUMP_IF_NONZERO     176
#define PRIMITIVE_UNBOX         177
#define PRIMITIVE_BINARY_OP     178
#define PRIMITIVE_UNARY_OP      179
#define PRIMITIVE_COMPARE_OP    180
#define LOAD_ITERABLE_ARG       181
#define LOAD_MAPPING_ARG        182
#define INVOKE_FUNCTION         183
#define JUMP_IF_ZERO_OR_POP     184
#define JUMP_IF_NONZERO_OR_POP  185
#define FAST_LEN                186
#define CONVERT_PRIMITIVE       187
#define CHECK_ARGS              188
#define LOAD_CLASS              190
#define BUILD_CHECKED_MAP       191
#define SEQUENCE_GET            192
#define SEQUENCE_SET            193
#define LIST_DEL                194
#define REFINE_TYPE             195
#define PRIMITIVE_LOAD_CONST    196
#define RETURN_PRIMITIVE        197
#define LOAD_METHOD_SUPER       198
#define LOAD_ATTR_SUPER         199
#define TP_ALLOC                200
#define BUILD_CHECKED_LIST      201
#define LOAD_TYPE               202
#define LOAD_METHOD_UNSHADOWED_METHOD 205
#define LOAD_METHOD_TYPE_METHODLIKE 206
#define BUILD_CHECKED_LIST_CACHED 207
#define TP_ALLOC_CACHED         208
#define LOAD_ATTR_S_MODULE      209
#define LOAD_METHOD_S_MODULE    210
#define INVOKE_FUNCTION_CACHED  211
#define INVOKE_FUNCTION_INDIRECT_CACHED 212
#define BUILD_CHECKED_MAP_CACHED 213
#define CHECK_ARGS_CACHED       214
#define PRIMITIVE_STORE_FAST    215
#define CAST_CACHED_OPTIONAL    216
#define CAST_CACHED             217
#define CAST_CACHED_EXACT       218
#define CAST_CACHED_OPTIONAL_EXACT 219
#define LOAD_PRIMITIVE_FIELD    220
#define STORE_PRIMITIVE_FIELD   221
#define LOAD_OBJ_FIELD          222
#define STORE_OBJ_FIELD         223
#define INVOKE_METHOD_CACHED    224
#define BINARY_SUBSCR_TUPLE_CONST_INT 225
#define BINARY_SUBSCR_DICT_STR  226
#define BINARY_SUBSCR_LIST      227
#define BINARY_SUBSCR_TUPLE     228
#define BINARY_SUBSCR_DICT      229
#define LOAD_METHOD_UNCACHABLE  230
#define LOAD_METHOD_MODULE      231
#define LOAD_METHOD_TYPE        232
#define LOAD_METHOD_SPLIT_DICT_DESCR 233
#define LOAD_METHOD_SPLIT_DICT_METHOD 234
#define LOAD_METHOD_DICT_DESCR  235
#define LOAD_METHOD_DICT_METHOD 236
#define LOAD_METHOD_NO_DICT_METHOD 237
#define LOAD_METHOD_NO_DICT_DESCR 238
#define STORE_ATTR_SLOT         239
#define STORE_ATTR_SPLIT_DICT   240
#define STORE_ATTR_DESCR        241
#define STORE_ATTR_UNCACHABLE   242
#define STORE_ATTR_DICT         243
#define LOAD_ATTR_POLYMORPHIC   244
#define LOAD_ATTR_SLOT          245
#define LOAD_ATTR_MODULE        246
#define LOAD_ATTR_TYPE          247
#define LOAD_ATTR_SPLIT_DICT_DESCR 248
#define LOAD_ATTR_SPLIT_DICT    249
#define LOAD_ATTR_DICT_NO_DESCR 250
#define LOAD_ATTR_NO_DICT_DESCR 251
#define LOAD_ATTR_DICT_DESCR    252
#define LOAD_ATTR_UNCACHABLE    253
#define LOAD_GLOBAL_CACHED      254
#define SHADOW_NOP              255
#ifdef NEED_OPCODE_JUMP_TABLES
static uint32_t _PyOpcode_RelativeJump[8] = {
    0U,
    0U,
    536870912U,
    67125248U,
    67141632U,
    0U,
    0U,
    0U,
};
static uint32_t _PyOpcode_Jump[8] = {
    0U,
    0U,
    536870912U,
    101695488U,
    67141632U,
    50429952U,
    0U,
    0U,
};
#endif /* OPCODE_TABLES */

/* EXCEPT_HANDLER is a special, implicit block type which is created when
   entering an except handler. It is not an opcode but we define it here
   as we want it to be available to both frameobject.c and ceval.c, while
   remaining private.*/
#define EXCEPT_HANDLER 257

#define HAS_ARG(op) ((op) >= HAVE_ARGUMENT)

#ifdef __cplusplus
}
#endif
#endif /* !Py_OPCODE_H */
